fine_python_pyrefly/__init__.py
fine_python_pyrefly/lint_handler.py
fine_python_pyrefly-0.1.0.dist-info/METADATA
fine_python_pyrefly-0.1.0.dist-info/WHEEL
fine_python_pyrefly-0.1.0.dist-info/top_level.txt
fine_python_pyrefly-0.1.0.dist-info/RECORD
